kisti_flydog_naver_news_crawler/__init__.py
kisti_flydog_naver_news_crawler/server.py
kisti_flydog_naver_news_crawler-0.1.0.dist-info/METADATA
kisti_flydog_naver_news_crawler-0.1.0.dist-info/WHEEL
kisti_flydog_naver_news_crawler-0.1.0.dist-info/entry_points.txt
kisti_flydog_naver_news_crawler-0.1.0.dist-info/RECORD
